asyncio_event_hub/__init__.py
asyncio_event_hub/controller.py
asyncio_event_hub/doc.py
asyncio_event_hub-1.1.0.dist-info/LICENSE
asyncio_event_hub-1.1.0.dist-info/METADATA
asyncio_event_hub-1.1.0.dist-info/WHEEL
asyncio_event_hub-1.1.0.dist-info/top_level.txt
asyncio_event_hub-1.1.0.dist-info/RECORD
