Metadata-Version: 2.1
Name: asyncio-event-hub
Version: 1.1.0
Summary: A library that provides users the ability to create event (loop) driven systems within the asyncio framework.
Author: David Hozic
Keywords: event,asyncio,event driven,event loop
Classifier: Programming Language :: Python :: 3
Classifier: License :: OSI Approved :: MIT License
Classifier: Operating System :: OS Independent
Requires-Python: >=3.8
License-File: LICENSE
Provides-Extra: docs
Requires-Dist: sphinx ==7.1.2 ; extra == 'docs'
Requires-Dist: sphinx-autobuild ==2021.3.14 ; extra == 'docs'
Requires-Dist: sphinx-copybutton ==0.5.2 ; extra == 'docs'
Requires-Dist: furo ==2023.8.17 ; extra == 'docs'
Requires-Dist: enum-tools[sphinx] ==0.10.0 ; extra == 'docs'
Requires-Dist: sphinx-design[furo] ==0.5.0 ; extra == 'docs'
Requires-Dist: readthedocs-sphinx-search ==0.3.1 ; extra == 'docs'
Requires-Dist: sphinxcontrib-svg2pdfconverter ==1.2.2 ; extra == 'docs'
